.class public Aluno
.super java/lang/Object

.field public id I
.field public notas [F

.method public <init>()V
    aload_0
    invokespecial java/lang/Object/<init>()V
    return
.end method
.method public static novoAluno(I)LAluno;
    .limit stack 25
    .limit locals 25

    new Aluno
    dup
    invokespecial Aluno/<init>()V
    astore 1
    aload 1
    iload 0
    putfield Aluno/id I
    aload 1
    iconst_4
    newarray float
    putfield Aluno/notas [F
    iconst_4
    istore 2
    iconst_0
    istore 3
L0:
    iload 3
    iload 2
    if_icmpge L1
    aload 1
    getfield Aluno/notas [F
    iload 3
    ldc 0.0
    fastore
    iinc 3 1
    goto L0
L1:
    aload 1
    areturn
.end method

.method public static definirNota(LAluno;IF)V
    .limit stack 25
    .limit locals 25

    iload 1
    iconst_0
    if_icmpge L1
    iconst_0
    iconst_1
    isub
    iload 1
    imul
    istore 1
L0:
L1:
    iload 1
    iconst_4
    irem
    istore 1
    aload 0
    getfield Aluno/notas [F
    iload 1
    fload 2
    fastore
    return
.end method

.method public static nota(LAluno;I)F
    .limit stack 25
    .limit locals 25

    iload 1
    iconst_0
    if_icmpge L1
    iconst_0
    iconst_1
    isub
    iload 1
    imul
    istore 1
L0:
L1:
    iload 1
    iconst_4
    irem
    istore 1
    aload 0
    getfield Aluno/notas [F
    iload 1
    faload
    freturn
.end method

.method public static imprimeAluno(LAluno;)V
    .limit stack 25
    .limit locals 25

    getstatic java/lang/System/out Ljava/io/PrintStream;
    bipush 65
    invokevirtual java/io/PrintStream/print(C)V
    getstatic java/lang/System/out Ljava/io/PrintStream;
    bipush 108
    invokevirtual java/io/PrintStream/print(C)V
    getstatic java/lang/System/out Ljava/io/PrintStream;
    bipush 117
    invokevirtual java/io/PrintStream/print(C)V
    getstatic java/lang/System/out Ljava/io/PrintStream;
    bipush 110
    invokevirtual java/io/PrintStream/print(C)V
    getstatic java/lang/System/out Ljava/io/PrintStream;
    bipush 111
    invokevirtual java/io/PrintStream/print(C)V
    getstatic java/lang/System/out Ljava/io/PrintStream;
    bipush 32
    invokevirtual java/io/PrintStream/print(C)V
    getstatic java/lang/System/out Ljava/io/PrintStream;
    aload 0
    getfield Aluno/id I
    invokevirtual java/io/PrintStream/print(I)V
    getstatic java/lang/System/out Ljava/io/PrintStream;
    bipush 32
    invokevirtual java/io/PrintStream/print(C)V
    iconst_4
    istore 1
    iconst_0
    istore 2
L0:
    iload 2
    iload 1
    if_icmpge L1
    getstatic java/lang/System/out Ljava/io/PrintStream;
    aload 0
    getfield Aluno/notas [F
    iload 2
    faload
    invokevirtual java/io/PrintStream/print(F)V
    getstatic java/lang/System/out Ljava/io/PrintStream;
    bipush 59
    invokevirtual java/io/PrintStream/print(C)V
    iinc 2 1
    goto L0
L1:
    getstatic java/lang/System/out Ljava/io/PrintStream;
    bipush 10
    invokevirtual java/io/PrintStream/print(C)V
    return
.end method

